pypinfo/__init__.py
pypinfo/__main__.py
pypinfo/cli.py
pypinfo/core.py
pypinfo/db.py
pypinfo/fields.py
pypinfo/py.typed
pypinfo-23.0.0.dist-info/METADATA
pypinfo-23.0.0.dist-info/WHEEL
pypinfo-23.0.0.dist-info/entry_points.txt
pypinfo-23.0.0.dist-info/licenses/AUTHORS.rst
pypinfo-23.0.0.dist-info/licenses/LICENSE.txt
pypinfo-23.0.0.dist-info/RECORD
