Metadata-Version: 2.4
Name: pypinfo
Version: 23.0.0
Summary: View PyPI download statistics with ease.
Project-URL: Changelog, https://github.com/ofek/pypinfo/blob/master/CHANGELOG.rst
Project-URL: Funding, https://github.com/sponsors/ofek
Project-URL: Issues, https://github.com/ofek/pypinfo/issues
Project-URL: Source, https://github.com/ofek/pypinfo
Author-email: Ofek Lev <oss@ofek.dev>
License-Expression: MIT
License-File: AUTHORS.rst
License-File: LICENSE.txt
Keywords: bigquery,downloads,pypi,stats
Classifier: Development Status :: 4 - Beta
Classifier: Intended Audience :: Developers
Classifier: Intended Audience :: End Users/Desktop
Classifier: License :: OSI Approved :: MIT License
Classifier: Natural Language :: English
Classifier: Operating System :: OS Independent
Classifier: Programming Language :: Python
Classifier: Programming Language :: Python :: 3
Classifier: Programming Language :: Python :: 3 :: Only
Classifier: Programming Language :: Python :: 3.10
Classifier: Programming Language :: Python :: 3.11
Classifier: Programming Language :: Python :: 3.12
Classifier: Programming Language :: Python :: 3.13
Classifier: Programming Language :: Python :: 3.14
Classifier: Programming Language :: Python :: Implementation :: CPython
Classifier: Programming Language :: Python :: Implementation :: PyPy
Requires-Python: >=3.10
Requires-Dist: binary
Requires-Dist: click
Requires-Dist: google-cloud-bigquery>=2.11.0
Requires-Dist: packaging>=16.2
Requires-Dist: platformdirs
Requires-Dist: tinydb>=4
Requires-Dist: tinyrecord>=0.2.0
